storage_viewer/__init__.py
storage_viewer/storage_viewer.py
storage_viewer_cli-0.5.0.dist-info/licenses/LICENSE
storage_viewer_cli-0.5.0.dist-info/METADATA
storage_viewer_cli-0.5.0.dist-info/WHEEL
storage_viewer_cli-0.5.0.dist-info/entry_points.txt
storage_viewer_cli-0.5.0.dist-info/top_level.txt
storage_viewer_cli-0.5.0.dist-info/RECORD
