Metadata-Version: 2.4
Name: storage-viewer-cli
Version: 0.5.0
Summary: Advanced directory tree visualizer with filtering options
Home-page: https://github.com/infofusiontechlab/storage-viewer
Author: Lingaraj Sa
Author-email: Lingaraj Sa <infofusiontechlab@gmail.com>
License: MIT
Project-URL: Homepage, https://github.com/infofusiontechlab/storage-viewer
Project-URL: Bug Tracker, https://github.com/infofusiontechlab/storage-viewer/issues
Classifier: Programming Language :: Python :: 3
Classifier: License :: OSI Approved :: MIT License
Classifier: Operating System :: OS Independent
Classifier: Operating System :: Android
Classifier: Environment :: Console
Requires-Python: >=3.7
License-File: LICENSE
Dynamic: author
Dynamic: home-page
Dynamic: license-file
Dynamic: requires-python
